LICENSE
MANIFEST.in
README.rst
pyproject.toml
setup.py
contrib/boost/boost/assert.hpp
contrib/boost/boost/call_traits.hpp
contrib/boost/boost/concept_check.hpp
contrib/boost/boost/config.hpp
contrib/boost/boost/cstdint.hpp
contrib/boost/boost/current_function.hpp
contrib/boost/boost/foreach_fwd.hpp
contrib/boost/boost/function.hpp
contrib/boost/boost/function_equal.hpp
contrib/boost/boost/get_pointer.hpp
contrib/boost/boost/integer.hpp
contrib/boost/boost/integer_fwd.hpp
contrib/boost/boost/integer_traits.hpp
contrib/boost/boost/is_placeholder.hpp
contrib/boost/boost/limits.hpp
contrib/boost/boost/mem_fn.hpp
contrib/boost/boost/multi_index_container.hpp
contrib/boost/boost/multi_index_container_fwd.hpp
contrib/boost/boost/noncopyable.hpp
contrib/boost/boost/operators.hpp
contrib/boost/boost/ref.hpp
contrib/boost/boost/static_assert.hpp
contrib/boost/boost/throw_exception.hpp
contrib/boost/boost/type.hpp
contrib/boost/boost/type_index.hpp
contrib/boost/boost/version.hpp
contrib/boost/boost/visit_each.hpp
contrib/boost/boost/archive/archive_exception.hpp
contrib/boost/boost/archive/detail/abi_prefix.hpp
contrib/boost/boost/archive/detail/abi_suffix.hpp
contrib/boost/boost/archive/detail/decl.hpp
contrib/boost/boost/assert/source_location.hpp
contrib/boost/boost/bind/arg.hpp
contrib/boost/boost/bind/bind.hpp
contrib/boost/boost/bind/bind_cc.hpp
contrib/boost/boost/bind/bind_mf2_cc.hpp
contrib/boost/boost/bind/bind_mf_cc.hpp
contrib/boost/boost/bind/bind_template.hpp
contrib/boost/boost/bind/mem_fn.hpp
contrib/boost/boost/bind/mem_fn_cc.hpp
contrib/boost/boost/bind/mem_fn_template.hpp
contrib/boost/boost/bind/mem_fn_vw.hpp
contrib/boost/boost/bind/placeholders.hpp
contrib/boost/boost/bind/storage.hpp
contrib/boost/boost/concept/assert.hpp
contrib/boost/boost/concept/usage.hpp
contrib/boost/boost/concept/detail/backward_compatibility.hpp
contrib/boost/boost/concept/detail/borland.hpp
contrib/boost/boost/concept/detail/concept_def.hpp
dSalmon.egg-info/PKG-INFO
dSalmon.egg-info/SOURCES.txt
dSalmon.egg-info/dependency_links.txt
dSalmon.egg-info/requires.txt
dSalmon.egg-info/top_level.txt
