Metadata-Version: 2.1
Name: dSalmon
Version: 0.1
Summary: dSalmon is a framework for analyzing data streams
Home-page: https://github.com/CN-TU/dSalmon
Author: Alexander Hartl
Author-email: alexander.hartl@tuwien.ac.at
License: LGPL-3.0
Project-URL: Source, https://github.com/CN-TU/dSalmon
Project-URL: Documentation, https://dSalmon.readthedocs.io
Project-URL: Tracker, https://github.com/CN-TU/dSalmon/issues
Platform: UNKNOWN
Classifier: Development Status :: 4 - Beta
Classifier: Intended Audience :: Developers
Classifier: Intended Audience :: Science/Research
Classifier: License :: OSI Approved :: GNU Lesser General Public License v3 (LGPLv3)
Classifier: Programming Language :: C++
Classifier: Programming Language :: Python :: 3
Classifier: Programming Language :: Python :: Implementation :: CPython
Classifier: Topic :: Scientific/Engineering
Requires-Python: >=3.5
License-File: LICENSE
